quantgrid_cli/__init__.py
quantgrid_cli/auth.py
quantgrid_cli/cli.py
quantgrid_cli/main.py
quantgrid_cli/requirements.txt
quantgrid_cli/__pycache__/__init__.cpython-312.pyc
quantgrid_cli/__pycache__/auth.cpython-312.pyc
quantgrid_cli/__pycache__/cli.cpython-312.pyc
quantgrid_cli/boilerplate/.env
quantgrid_cli/boilerplate/README.md
quantgrid_cli/boilerplate/config.py
quantgrid_cli/boilerplate/main.py
quantgrid_cli/boilerplate/requirements.txt
quantgrid_cli/boilerplate/lib/base.py
quantgrid_cli/boilerplate/lib/data_preparation.py
quantgrid_cli/boilerplate/lib/data_provider.py
quantgrid_cli/boilerplate/lib/experiment_runner.py
quantgrid_cli/boilerplate/lib/metrics.py
quantgrid_cli/boilerplate/lib/mlflow_utils.py
quantgrid_cli/boilerplate/lib/models.py
quantgrid_cli/boilerplate/lib/scalers.py
quantgrid_cli/boilerplate/lib/scanner.py
quantgrid_cli/boilerplate/lib/strategies.py
quantgrid_cli-0.1.4.dist-info/METADATA
quantgrid_cli-0.1.4.dist-info/WHEEL
quantgrid_cli-0.1.4.dist-info/entry_points.txt
quantgrid_cli-0.1.4.dist-info/top_level.txt
quantgrid_cli-0.1.4.dist-info/RECORD
